Metadata-Version: 2.1
Name: myfpl
Version: 2.4.2
Summary: A useful module
Home-page: https://github.com/trozler/myfpl
Author: trozler
Author-email: tony.rosler246@gmail.com
License: MIT
Keywords: fpl,fantasy premier league,cli,command line
Platform: UNKNOWN
Classifier: Programming Language :: Python :: 3
Classifier: License :: OSI Approved :: MIT License
Classifier: Operating System :: OS Independent
